docs_to_md/__init__.py
docs_to_md/__main__.py
docs_to_md/main.py
docs_to_md/api/__init__.py
docs_to_md/api/client.py
docs_to_md/api/models.py
docs_to_md/config/__init__.py
docs_to_md/config/cli.py
docs_to_md/config/settings.py
docs_to_md/core/__init__.py
docs_to_md/core/paths.py
docs_to_md/core/processor.py
docs_to_md/core/result_handler.py
docs_to_md/storage/__init__.py
docs_to_md/storage/cache.py
docs_to_md/storage/models.py
docs_to_md/utils/__init__.py
docs_to_md/utils/exceptions.py
docs_to_md/utils/file_utils.py
docs_to_md/utils/logging.py
docs_to_md/utils/pdf_splitter.py
pdf_to_markdown_cli-0.5.1.dist-info/licenses/LICENSE
pdf_to_markdown_cli-0.5.1.dist-info/METADATA
pdf_to_markdown_cli-0.5.1.dist-info/WHEEL
pdf_to_markdown_cli-0.5.1.dist-info/entry_points.txt
pdf_to_markdown_cli-0.5.1.dist-info/top_level.txt
pdf_to_markdown_cli-0.5.1.dist-info/RECORD
