Metadata-Version: 2.4
Name: pdf-to-markdown-cli
Version: 0.5.1
Summary: CLI tool to convert PDF files (and other documents) to markdown using the Marker API.
Author: Nikita Sokolsky
License: MIT License
Project-URL: Homepage, https://github.com/SokolskyNikita/pdf-to-markdown-cli
Project-URL: Bug Tracker, https://github.com/SokolskyNikita/pdf-to-markdown-cli/issues
Keywords: pdf,markdown,converter,cli,document,marker,md
Classifier: Development Status :: 4 - Beta
Classifier: Intended Audience :: Developers
Classifier: Intended Audience :: End Users/Desktop
Classifier: License :: OSI Approved :: MIT License
Classifier: Programming Language :: Python :: 3
Classifier: Programming Language :: Python :: 3.10
Classifier: Programming Language :: Python :: 3.11
Classifier: Programming Language :: Python :: 3.12
Classifier: Operating System :: OS Independent
Classifier: Topic :: Text Processing
Classifier: Topic :: Utilities
Requires-Python: >=3.10
License-File: LICENSE
Requires-Dist: backoff>=2.0
Requires-Dist: diskcache>=5.0
Requires-Dist: filetype>=1.0
Requires-Dist: pikepdf>=8.0
Requires-Dist: pydantic>=2.0
Requires-Dist: ratelimit>=2.0
Requires-Dist: requests>=2.0
Requires-Dist: tqdm>=4.0
Provides-Extra: test
Dynamic: license-file
